lemon/StartDevServer.py
lemon/default.zip
lemon/lemonCreate.py
lemon/path.py
lemon/webserver.py
lemon/wsgi.py
lemon/default/main.py
lemon/default/wsgi.py
lemon/default/app/urls.py
lemon/default/app/web.py
lemon/default/app/extensions/WAF/file.py
lemon/default/app/extensions/python_cgi/cgi.py
lemon/default/app/log/log.txt
lemon/default/config/config.py
lemon/default/config/ssl/readme.txt
lemon/libs/Date.py
lemon/libs/HttpObject.py
lemon/libs/__init__.py
lemon/libs/colors.py
lemon/libs/create_http.py
lemon/libs/errors.py
lemon/libs/extensions.py
lemon/libs/file.py
lemon/libs/file_extensions.py
lemon/libs/form_handle.py
lemon/libs/handleHttp.py
lemon/libs/http_status.py
lemon/libs/lemon.py
lemon/libs/logging.py
lemon/libs/multipart_formdata.py
lemon/libs/route.py
lemon/libs/url_validation.py
lemon_framework-1.3.4.dist-info/LICENSE
lemon_framework-1.3.4.dist-info/METADATA
lemon_framework-1.3.4.dist-info/WHEEL
lemon_framework-1.3.4.dist-info/top_level.txt
lemon_framework-1.3.4.dist-info/RECORD
