Metadata-Version: 2.1
Name: lemon-framework
Version: 1.3.4
Summary: Web framework written in python
Home-page: https://github.com/InsaneMiner/Lemon
Author: Joel Schofield
Author-email: none@none.none
License: LICENSE
Platform: UNKNOWN
Classifier: Programming Language :: Python :: 3
Classifier: License :: OSI Approved :: MIT License
Classifier: Operating System :: OS Independent
Requires-Python: >=3.6
Requires-Dist: asyncio
Requires-Dist: jinja2
Requires-Dist: regex
Requires-Dist: urllib3
Requires-Dist: watchdog
